pathtools/__init__.py
pathtools/path.py
pathtools/patterns.py
pathtools/version.py
pathtools3-0.2.1.dist-info/LICENSE.txt
pathtools3-0.2.1.dist-info/METADATA
pathtools3-0.2.1.dist-info/RECORD
pathtools3-0.2.1.dist-info/WHEEL
pathtools3-0.2.1.dist-info/top_level.txt
